test_average/__init__.py
test_average/average.py
popeye_ob-1.0.15.dist-info/METADATA
popeye_ob-1.0.15.dist-info/WHEEL
popeye_ob-1.0.15.dist-info/top_level.txt
popeye_ob-1.0.15.dist-info/RECORD
