Metadata-Version: 2.1
Name: popeye-ob
Version: 1.0.15
Summary: A test package to demonstrate heee pip packages
Home-page: https://github.com/teja156/autobot-clipper
Author: hackz boy shyam
Author-email: popeye@example.com
Project-URL: Bug Tracker, https://github.com/teja156/autobot-clipper/issues
Classifier: Programming Language :: Python :: 3
Classifier: License :: OSI Approved :: MIT License
Classifier: Operating System :: OS Independent
Requires-Python: >=3.6
